<annotaion>
  <folder>Pascal_Voc</folder>
  <filename>689908.jpg</filename>
  <size>
    <width>1280</width>
    <height>720</height>
    <depth>3</depth>
  </size>
  <segmented>0</segmented>
  <object>
    <name>Green</name>
    <pose>Unspecified</pose>
    <occluded>False</occluded>
    <difficult>0</difficult>
    <bndbox>
      <xmin>605.1857701408</xmin>
      <ymin>240.5365598481</ymin>
      <xmax>614.5327686767</xmax>
      <ymax>259.453104504</ymax>
    </bndbox>
  </object>
  <object>
    <name>Green</name>
    <pose>Unspecified</pose>
    <occluded>False</occluded>
    <difficult>0</difficult>
    <bndbox>
      <xmin>620.28111458</xmin>
      <ymin>290.5619773931</ymin>
      <xmax>623.9077608865</xmax>
      <ymax>299.2659285288</ymax>
    </bndbox>
  </object>
  <object>
    <name>Green</name>
    <pose>Unspecified</pose>
    <occluded>False</occluded>
    <difficult>0</difficult>
    <bndbox>
      <xmin>711.1305907277</xmin>
      <ymin>273.2000668152</ymin>
      <xmax>718.0295658375</xmax>
      <ymax>284.5499936087</ymax>
    </bndbox>
  </object>
  <object>
    <name>Green</name>
    <pose>Unspecified</pose>
    <occluded>False</occluded>
    <difficult>0</difficult>
    <bndbox>
      <xmin>742.5098000981</xmin>
      <ymin>260.0697593481</ymin>
      <xmax>754.3048220601</xmax>
      <ymax>284.5499936087</ymax>
    </bndbox>
  </object>
</annotaion>
